cortexable/__init__.py
cortexable/core.py
cortexable-0.1.0.dist-info/METADATA
cortexable-0.1.0.dist-info/WHEEL
cortexable-0.1.0.dist-info/top_level.txt
cortexable-0.1.0.dist-info/RECORD
